[
    {
        "elapsed": 2.625,
        "longname": "behemoth0",
        "name": "behemoth0",
        "status": "up",
        "timestamp": 1615988862.4223535
    },
    {
        "elapsed": 0.676,
        "longname": "behemoth0 > 1",
        "name": "behemoth1",
        "status": "up",
        "timestamp": 1615988862.4224558
    },
    {
        "elapsed": 0.671,
        "longname": "behemoth1 > 2",
        "name": "behemoth2",
        "status": "up",
        "timestamp": 1615988862.4225075
    },
    {
        "elapsed": 0.772,
        "longname": "behemoth2 > 3",
        "name": "behemoth3",
        "status": "up",
        "timestamp": 1615988862.4225557
    },
    {
        "elapsed": 3.613,
        "longname": "behemoth3 > 4",
        "name": "behemoth4",
        "status": "down",
        "timestamp": 1615988862.422611
    },
    {
        "elapsed": 1.775,
        "longname": "behemoth4 > 5",
        "name": "behemoth5",
        "status": "up",
        "timestamp": 1615988862.422653
    },
    {
        "elapsed": 1.608,
        "longname": "behemoth5 > 6",
        "name": "behemoth6",
        "status": "up",
        "timestamp": 1615988862.422692
    },
    {
        "elapsed": 0.774,
        "longname": "behemoth6 > 7",
        "name": "behemoth7",
        "status": "up",
        "timestamp": 1615988862.4227257
    },
    {
        "elapsed": 0.642,
        "longname": "behemoth7 > 8",
        "name": "behemoth8",
        "status": "up",
        "timestamp": 1615988862.4227605
    }
]