[
    {
        "elapsed": 0.073,
        "longname": "natas0",
        "name": "natas0",
        "status": "up",
        "timestamp": 1659747846.9116867
    },
    {
        "elapsed": 0.057,
        "longname": "natas0 > 1",
        "name": "natas1",
        "status": "up",
        "timestamp": 1659747846.9130826
    },
    {
        "elapsed": 0.067,
        "longname": "natas1 > 2",
        "name": "natas2",
        "status": "up",
        "timestamp": 1659747846.913384
    },
    {
        "elapsed": 0.18,
        "longname": "natas2 > 3",
        "name": "natas3",
        "status": "up",
        "timestamp": 1659747846.9136689
    },
    {
        "elapsed": 0.204,
        "longname": "natas3 > 4",
        "name": "natas4",
        "status": "up",
        "timestamp": 1659747846.9138298
    },
    {
        "elapsed": 0.066,
        "longname": "natas4 > 5",
        "name": "natas5",
        "status": "up",
        "timestamp": 1659747846.9138548
    },
    {
        "elapsed": 0.123,
        "longname": "natas5 > 6",
        "name": "natas6",
        "status": "up",
        "timestamp": 1659747846.9138784
    },
    {
        "elapsed": 0.236,
        "longname": "natas6 > 7",
        "name": "natas7",
        "status": "up",
        "timestamp": 1659747846.9139023
    },
    {
        "elapsed": 0.125,
        "longname": "natas7 > 8",
        "name": "natas8",
        "status": "up",
        "timestamp": 1659747846.913927
    },
    {
        "elapsed": 0.193,
        "longname": "natas8 > 9",
        "name": "natas9",
        "status": "up",
        "timestamp": 1659747846.9139514
    },
    {
        "elapsed": 0.193,
        "longname": "natas9 > 10",
        "name": "natas10",
        "status": "up",
        "timestamp": 1659747846.91312
    },
    {
        "elapsed": 0.184,
        "longname": "natas10 > 11",
        "name": "natas11",
        "status": "up",
        "timestamp": 1659747846.9131496
    },
    {
        "elapsed": 0.187,
        "longname": "natas11 > 12",
        "name": "natas12",
        "status": "up",
        "timestamp": 1659747846.9131773
    },
    {
        "elapsed": 0.306,
        "longname": "natas12 > 13",
        "name": "natas13",
        "status": "up",
        "timestamp": 1659747846.9132037
    },
    {
        "elapsed": 0.309,
        "longname": "natas13 > 14",
        "name": "natas14",
        "status": "up",
        "timestamp": 1659747846.9132307
    },
    {
        "elapsed": 0.186,
        "longname": "natas14 > 15",
        "name": "natas15",
        "status": "up",
        "timestamp": 1659747846.913256
    },
    {
        "elapsed": 4.127,
        "longname": "natas15 > 16",
        "name": "natas16",
        "status": "up",
        "timestamp": 1659747846.9132824
    },
    {
        "elapsed": 1.638,
        "longname": "natas16 > 17",
        "name": "natas17",
        "status": "up",
        "timestamp": 1659747846.9133077
    },
    {
        "elapsed": 8.144,
        "longname": "natas17 > 18",
        "name": "natas18",
        "status": "up",
        "timestamp": 1659747846.9133337
    },
    {
        "elapsed": 2.415,
        "longname": "natas18 > 19",
        "name": "natas19",
        "status": "up",
        "timestamp": 1659747846.913359
    },
    {
        "elapsed": 0.896,
        "longname": "natas19 > 20",
        "name": "natas20",
        "status": "up",
        "timestamp": 1659747846.9134092
    },
    {
        "elapsed": 0.861,
        "longname": "natas20 > 21",
        "name": "natas21",
        "status": "down",
        "timestamp": 1659747846.9134467
    },
    {
        "elapsed": 0.369,
        "longname": "natas21 > 22",
        "name": "natas22",
        "status": "up",
        "timestamp": 1659747846.9134722
    },
    {
        "elapsed": 0.193,
        "longname": "natas22 > 23",
        "name": "natas23",
        "status": "up",
        "timestamp": 1659747846.9134974
    },
    {
        "elapsed": 0.184,
        "longname": "natas23 > 24",
        "name": "natas24",
        "status": "up",
        "timestamp": 1659747846.913523
    },
    {
        "elapsed": 0.184,
        "longname": "natas24 > 25",
        "name": "natas25",
        "status": "up",
        "timestamp": 1659747846.9135478
    },
    {
        "elapsed": 0.205,
        "longname": "natas25 > 26",
        "name": "natas26",
        "status": "up",
        "timestamp": 1659747846.9135718
    },
    {
        "elapsed": 0.269,
        "longname": "natas26 > 27",
        "name": "natas27",
        "status": "up",
        "timestamp": 1659747846.9135962
    },
    {
        "elapsed": 0.317,
        "longname": "natas27 > 28",
        "name": "natas28",
        "status": "up",
        "timestamp": 1659747846.9136205
    },
    {
        "elapsed": 0.163,
        "longname": "natas28 > 29",
        "name": "natas29",
        "status": "up",
        "timestamp": 1659747846.9136446
    },
    {
        "elapsed": 0.33,
        "longname": "natas29 > 30",
        "name": "natas30",
        "status": "up",
        "timestamp": 1659747846.913694
    },
    {
        "elapsed": 0.359,
        "longname": "natas30 > 31",
        "name": "natas31",
        "status": "up",
        "timestamp": 1659747846.9137182
    },
    {
        "elapsed": 0.309,
        "longname": "natas31 > 32",
        "name": "natas32",
        "status": "up",
        "timestamp": 1659747846.9137533
    },
    {
        "elapsed": 0.331,
        "longname": "natas32 > 33",
        "name": "natas33",
        "status": "up",
        "timestamp": 1659747846.913779
    },
    {
        "elapsed": 0.278,
        "longname": "natas33 > 34",
        "name": "natas34",
        "status": "up",
        "timestamp": 1659747846.9138036
    }
]