[
    {
        "elapsed": 2.375,
        "longname": "leviathan0",
        "name": "leviathan0",
        "status": "up",
        "timestamp": 1641058369.1592355
    },
    {
        "elapsed": 0.637,
        "longname": "leviathan0 > 1",
        "name": "leviathan1",
        "status": "up",
        "timestamp": 1641058369.1593204
    },
    {
        "elapsed": 0.624,
        "longname": "leviathan1 > 2",
        "name": "leviathan2",
        "status": "up",
        "timestamp": 1641058369.1593506
    },
    {
        "elapsed": 0.632,
        "longname": "leviathan2 > 3",
        "name": "leviathan3",
        "status": "up",
        "timestamp": 1641058369.1593773
    },
    {
        "elapsed": 0.631,
        "longname": "leviathan3 > 4",
        "name": "leviathan4",
        "status": "up",
        "timestamp": 1641058369.1594357
    },
    {
        "elapsed": 0.622,
        "longname": "leviathan4 > 5",
        "name": "leviathan5",
        "status": "up",
        "timestamp": 1641058369.1594632
    },
    {
        "elapsed": 0.902,
        "longname": "leviathan5 > 6",
        "name": "leviathan6",
        "status": "up",
        "timestamp": 1641058369.1594875
    },
    {
        "elapsed": 0.619,
        "longname": "leviathan6 > 7",
        "name": "leviathan7",
        "status": "up",
        "timestamp": 1641058369.1595116
    }
]