[
    {
        "elapsed": 2.837,
        "longname": "utumno0",
        "name": "utumno0",
        "status": "up",
        "timestamp": 1647904755.539584
    },
    {
        "elapsed": 0.74,
        "longname": "utumno0 > 1",
        "name": "utumno1",
        "status": "up",
        "timestamp": 1647904755.5396502
    },
    {
        "elapsed": 0.717,
        "longname": "utumno1 > 2",
        "name": "utumno2",
        "status": "up",
        "timestamp": 1647904755.5396802
    },
    {
        "elapsed": 0.86,
        "longname": "utumno2 > 3",
        "name": "utumno3",
        "status": "up",
        "timestamp": 1647904755.5397067
    },
    {
        "elapsed": 0.798,
        "longname": "utumno3 > 4",
        "name": "utumno4",
        "status": "up",
        "timestamp": 1647904755.5397308
    },
    {
        "elapsed": 0.782,
        "longname": "utumno4 > 5",
        "name": "utumno5",
        "status": "up",
        "timestamp": 1647904755.5397544
    },
    {
        "elapsed": 0.846,
        "longname": "utumno5 > 6",
        "name": "utumno5",
        "status": "up",
        "timestamp": 1647904755.5397778
    },
    {
        "elapsed": 1.07,
        "longname": "utumno6 > 7",
        "name": "utumno7",
        "status": "up",
        "timestamp": 1647904755.5398006
    },
    {
        "elapsed": 0.77,
        "longname": "utumno7 > 8",
        "name": "utumno8",
        "status": "up",
        "timestamp": 1647904755.5398235
    }
]