[
    {
        "elapsed": 2.407,
        "longname": "narnia0",
        "name": "narnia0",
        "status": "up",
        "timestamp": 1627238007.7010322
    },
    {
        "elapsed": 0.626,
        "longname": "narnia0 > 1",
        "name": "narnia1",
        "status": "up",
        "timestamp": 1627238007.7011054
    },
    {
        "elapsed": 0.722,
        "longname": "narnia1 > 2",
        "name": "narnia2",
        "status": "up",
        "timestamp": 1627238007.7011423
    },
    {
        "elapsed": 0.659,
        "longname": "narnia2 > 3",
        "name": "narnia3",
        "status": "up",
        "timestamp": 1627238007.7011766
    },
    {
        "elapsed": 0.647,
        "longname": "narnia3 > 4",
        "name": "narnia4",
        "status": "up",
        "timestamp": 1627238007.70121
    },
    {
        "elapsed": 0.653,
        "longname": "narnia4 > 5",
        "name": "narnia5",
        "status": "up",
        "timestamp": 1627238007.7012432
    },
    {
        "elapsed": 1.309,
        "longname": "narnia5 > 6",
        "name": "narnia6",
        "status": "up",
        "timestamp": 1627238007.7012756
    },
    {
        "elapsed": 0.66,
        "longname": "narnia6 > 7",
        "name": "narnia7",
        "status": "up",
        "timestamp": 1627238007.7013083
    },
    {
        "elapsed": 2.666,
        "longname": "narnia7 > 8",
        "name": "narnia8",
        "status": "up",
        "timestamp": 1627238007.701341
    },
    {
        "elapsed": 0.818,
        "longname": "narnia8 > 9",
        "name": "narnia9",
        "status": "up",
        "timestamp": 1627238007.701374
    }
]