[
    {
        "elapsed": 2.341,
        "longname": "manpage0",
        "name": "manpage0",
        "status": "up",
        "timestamp": 1661113079.363159
    },
    {
        "elapsed": 1.276,
        "longname": "manpage0>1",
        "name": "manpage1",
        "status": "up",
        "timestamp": 1661113079.3631885
    },
    {
        "elapsed": 1.391,
        "longname": "manpage1>2",
        "name": "manpage2",
        "status": "up",
        "timestamp": 1661113079.3632345
    },
    {
        "elapsed": 1.535,
        "longname": "manpage2>3",
        "name": "manpage3",
        "status": "up",
        "timestamp": 1661113079.363261
    },
    {
        "elapsed": 1.393,
        "longname": "manpage3>4",
        "name": "manpage4",
        "status": "up",
        "timestamp": 1661113079.3632867
    },
    {
        "elapsed": 1.472,
        "longname": "manpage4>5",
        "name": "manpage5",
        "status": "up",
        "timestamp": 1661113079.3633122
    },
    {
        "elapsed": 1.291,
        "longname": "manpage5 > 6",
        "name": "manpage6",
        "status": "up",
        "timestamp": 1661113079.363337
    },
    {
        "elapsed": 0.003,
        "longname": "manpage6 > 7",
        "name": "manpage7",
        "status": "unknown",
        "timestamp": 1661113079.3630912
    }
]