[
    {
        "elapsed": 2.331,
        "longname": "narnia0",
        "name": "narnia0",
        "status": "up",
        "timestamp": 1621294403.558777
    },
    {
        "elapsed": 0.628,
        "longname": "narnia0 > 1",
        "name": "narnia1",
        "status": "up",
        "timestamp": 1621294403.558852
    },
    {
        "elapsed": 0.671,
        "longname": "narnia1 > 2",
        "name": "narnia2",
        "status": "up",
        "timestamp": 1621294403.5588896
    },
    {
        "elapsed": 0.691,
        "longname": "narnia2 > 3",
        "name": "narnia3",
        "status": "up",
        "timestamp": 1621294403.5589252
    },
    {
        "elapsed": 0.639,
        "longname": "narnia3 > 4",
        "name": "narnia4",
        "status": "up",
        "timestamp": 1621294403.5589588
    },
    {
        "elapsed": 0.646,
        "longname": "narnia4 > 5",
        "name": "narnia5",
        "status": "up",
        "timestamp": 1621294403.5589921
    },
    {
        "elapsed": 1.258,
        "longname": "narnia5 > 6",
        "name": "narnia6",
        "status": "up",
        "timestamp": 1621294403.5590258
    },
    {
        "elapsed": 0.63,
        "longname": "narnia6 > 7",
        "name": "narnia7",
        "status": "up",
        "timestamp": 1621294403.5590603
    },
    {
        "elapsed": 2.629,
        "longname": "narnia7 > 8",
        "name": "narnia8",
        "status": "up",
        "timestamp": 1621294403.5590935
    },
    {
        "elapsed": 0.82,
        "longname": "narnia8 > 9",
        "name": "narnia9",
        "status": "up",
        "timestamp": 1621294403.5591269
    }
]