[
    {
        "elapsed": 2.38,
        "longname": "narnia0",
        "name": "narnia0",
        "status": "up",
        "timestamp": 1653928404.2248232
    },
    {
        "elapsed": 0.628,
        "longname": "narnia0 > 1",
        "name": "narnia1",
        "status": "up",
        "timestamp": 1653928404.224907
    },
    {
        "elapsed": 0.681,
        "longname": "narnia1 > 2",
        "name": "narnia2",
        "status": "up",
        "timestamp": 1653928404.2249389
    },
    {
        "elapsed": 0.633,
        "longname": "narnia2 > 3",
        "name": "narnia3",
        "status": "up",
        "timestamp": 1653928404.2249663
    },
    {
        "elapsed": 0.611,
        "longname": "narnia3 > 4",
        "name": "narnia4",
        "status": "up",
        "timestamp": 1653928404.224992
    },
    {
        "elapsed": 0.632,
        "longname": "narnia4 > 5",
        "name": "narnia5",
        "status": "up",
        "timestamp": 1653928404.225018
    },
    {
        "elapsed": 1.262,
        "longname": "narnia5 > 6",
        "name": "narnia6",
        "status": "up",
        "timestamp": 1653928404.2250435
    },
    {
        "elapsed": 0.629,
        "longname": "narnia6 > 7",
        "name": "narnia7",
        "status": "up",
        "timestamp": 1653928404.2250683
    },
    {
        "elapsed": 2.636,
        "longname": "narnia7 > 8",
        "name": "narnia8",
        "status": "up",
        "timestamp": 1653928404.2251618
    },
    {
        "elapsed": 0.839,
        "longname": "narnia8 > 9",
        "name": "narnia9",
        "status": "up",
        "timestamp": 1653928404.225201
    }
]