[
    {
        "elapsed": 0.001,
        "longname": "vortex0 > 1",
        "name": "vortex1",
        "status": "unknown",
        "timestamp": 1635700773.998354
    },
    {
        "elapsed": 0.001,
        "longname": "vortex1 > 2",
        "name": "vortex2",
        "status": "unknown",
        "timestamp": 1635700773.9984183
    },
    {
        "elapsed": 0.001,
        "longname": "vortex2 > 3",
        "name": "vortex3",
        "status": "unknown",
        "timestamp": 1635700773.9984586
    },
    {
        "elapsed": 0.001,
        "longname": "vortex3 > 4",
        "name": "vortex4",
        "status": "unknown",
        "timestamp": 1635700773.9984965
    },
    {
        "elapsed": 0.001,
        "longname": "vortex4 > 5",
        "name": "vortex5",
        "status": "unknown",
        "timestamp": 1635700773.9985337
    },
    {
        "elapsed": 0.001,
        "longname": "vortex5 > 6",
        "name": "vortex6",
        "status": "unknown",
        "timestamp": 1635700773.9985702
    },
    {
        "elapsed": 0.001,
        "longname": "vortex6 > 7",
        "name": "vortex7",
        "status": "unknown",
        "timestamp": 1635700773.9986072
    },
    {
        "elapsed": 0.001,
        "longname": "vortex7 > 8",
        "name": "vortex8",
        "status": "unknown",
        "timestamp": 1635700773.9986432
    },
    {
        "elapsed": 0.001,
        "longname": "vortex8 > 9",
        "name": "vortex9",
        "status": "unknown",
        "timestamp": 1635700773.9986813
    },
    {
        "elapsed": 0.001,
        "longname": "vortex9 > 10",
        "name": "vortex10",
        "status": "unknown",
        "timestamp": 1635700773.9987369
    },
    {
        "elapsed": 0.001,
        "longname": "vortex10 > 11",
        "name": "vortex11",
        "status": "unknown",
        "timestamp": 1635700773.9987926
    },
    {
        "elapsed": 0.001,
        "longname": "vortex11 > 12",
        "name": "vortex12",
        "status": "unknown",
        "timestamp": 1635700773.9988313
    },
    {
        "elapsed": 0.001,
        "longname": "vortex12 > 13",
        "name": "vortex13",
        "status": "unknown",
        "timestamp": 1635700773.998869
    },
    {
        "elapsed": 0.001,
        "longname": "vortex13 > 14",
        "name": "vortex14",
        "status": "unknown",
        "timestamp": 1635700773.9989064
    },
    {
        "elapsed": 0.001,
        "longname": "vortex14 > 15",
        "name": "vortex15",
        "status": "unknown",
        "timestamp": 1635700773.9989438
    },
    {
        "elapsed": 0.001,
        "longname": "vortex15 > 16",
        "name": "vortex16",
        "status": "unknown",
        "timestamp": 1635700773.9989812
    },
    {
        "elapsed": 0.001,
        "longname": "vortex16 > 17",
        "name": "vortex17",
        "status": "unknown",
        "timestamp": 1635700773.9990199
    },
    {
        "elapsed": 0.001,
        "longname": "vortex17 > 18",
        "name": "vortex18",
        "status": "unknown",
        "timestamp": 1635700773.9990573
    },
    {
        "elapsed": 0.001,
        "longname": "vortex18 > 19",
        "name": "vortex19",
        "status": "unknown",
        "timestamp": 1635700773.999095
    },
    {
        "elapsed": 0.001,
        "longname": "vortex19 > 20",
        "name": "vortex20",
        "status": "unknown",
        "timestamp": 1635700773.9991326
    },
    {
        "elapsed": 0.068,
        "longname": "vortex20 > 21",
        "name": "vortex21",
        "status": "unknown",
        "timestamp": 1635700773.9991698
    },
    {
        "elapsed": 0.001,
        "longname": "vortex21 > 22",
        "name": "vortex22",
        "status": "unknown",
        "timestamp": 1635700773.9992077
    },
    {
        "elapsed": 0.001,
        "longname": "vortex22 > 23",
        "name": "vortex23",
        "status": "unknown",
        "timestamp": 1635700773.999273
    },
    {
        "elapsed": 0.001,
        "longname": "vortex23 > 24",
        "name": "vortex24",
        "status": "unknown",
        "timestamp": 1635700773.9993174
    },
    {
        "elapsed": 0.002,
        "longname": "vortex24 > 25",
        "name": "vortex25",
        "status": "unknown",
        "timestamp": 1635700773.9993556
    }
]