[
    {
        "elapsed": 2.768,
        "longname": "behemoth0",
        "name": "behemoth0",
        "status": "up",
        "timestamp": 1630941452.1953278
    },
    {
        "elapsed": 0.672,
        "longname": "behemoth0 > 1",
        "name": "behemoth1",
        "status": "up",
        "timestamp": 1630941452.1954305
    },
    {
        "elapsed": 0.714,
        "longname": "behemoth1 > 2",
        "name": "behemoth2",
        "status": "up",
        "timestamp": 1630941452.1954782
    },
    {
        "elapsed": 0.76,
        "longname": "behemoth2 > 3",
        "name": "behemoth3",
        "status": "up",
        "timestamp": 1630941452.1955237
    },
    {
        "elapsed": 0.719,
        "longname": "behemoth3 > 4",
        "name": "behemoth4",
        "status": "up",
        "timestamp": 1630941452.1955652
    },
    {
        "elapsed": 1.784,
        "longname": "behemoth4 > 5",
        "name": "behemoth5",
        "status": "up",
        "timestamp": 1630941452.1956065
    },
    {
        "elapsed": 1.616,
        "longname": "behemoth5 > 6",
        "name": "behemoth6",
        "status": "up",
        "timestamp": 1630941452.195647
    },
    {
        "elapsed": 0.792,
        "longname": "behemoth6 > 7",
        "name": "behemoth7",
        "status": "up",
        "timestamp": 1630941452.1956868
    },
    {
        "elapsed": 0.658,
        "longname": "behemoth7 > 8",
        "name": "behemoth8",
        "status": "up",
        "timestamp": 1630941452.1957278
    }
]