[
    {
        "elapsed": 2.409,
        "longname": "manpage0",
        "name": "manpage0",
        "status": "up",
        "timestamp": 1639747077.210434
    },
    {
        "elapsed": 1.173,
        "longname": "manpage0>1",
        "name": "manpage1",
        "status": "up",
        "timestamp": 1639747077.2104619
    },
    {
        "elapsed": 1.399,
        "longname": "manpage1>2",
        "name": "manpage2",
        "status": "up",
        "timestamp": 1639747077.2104888
    },
    {
        "elapsed": 1.496,
        "longname": "manpage2>3",
        "name": "manpage3",
        "status": "up",
        "timestamp": 1639747077.2105145
    },
    {
        "elapsed": 1.401,
        "longname": "manpage3>4",
        "name": "manpage4",
        "status": "up",
        "timestamp": 1639747077.2105389
    },
    {
        "elapsed": 1.445,
        "longname": "manpage4>5",
        "name": "manpage5",
        "status": "up",
        "timestamp": 1639747077.2105737
    },
    {
        "elapsed": 0.001,
        "longname": "manpage5 > 6",
        "name": "manpage6",
        "status": "unknown",
        "timestamp": 1639747077.2103248
    },
    {
        "elapsed": 0.001,
        "longname": "manpage6 > 7",
        "name": "manpage7",
        "status": "unknown",
        "timestamp": 1639747077.2104023
    }
]