[
    {
        "elapsed": 0.001,
        "name": "krypton0",
        "status": "unknown",
        "timestamp": 1613282732.3268762
    },
    {
        "elapsed": 0.001,
        "name": "krypton1",
        "status": "unknown",
        "timestamp": 1613282732.3269262
    },
    {
        "elapsed": 0.001,
        "name": "krypton2",
        "status": "unknown",
        "timestamp": 1613282732.3269522
    },
    {
        "elapsed": 0.001,
        "name": "krypton3",
        "status": "unknown",
        "timestamp": 1613282732.3269746
    },
    {
        "elapsed": 0.001,
        "name": "krypton4",
        "status": "unknown",
        "timestamp": 1613282732.3269966
    },
    {
        "elapsed": 0.001,
        "name": "krypton5",
        "status": "unknown",
        "timestamp": 1613282732.3270185
    },
    {
        "elapsed": 0.001,
        "name": "krypton6",
        "status": "unknown",
        "timestamp": 1613282732.327041
    },
    {
        "elapsed": 0.001,
        "name": "krypton7",
        "status": "unknown",
        "timestamp": 1613282732.3270624
    }
]