[
    {
        "elapsed": 2.561,
        "longname": "utumno0",
        "name": "utumno0",
        "status": "up",
        "timestamp": 1622802854.5675623
    },
    {
        "elapsed": 0.658,
        "longname": "utumno0 > 1",
        "name": "utumno1",
        "status": "up",
        "timestamp": 1622802854.567635
    },
    {
        "elapsed": 0.645,
        "longname": "utumno1 > 2",
        "name": "utumno2",
        "status": "up",
        "timestamp": 1622802854.567672
    },
    {
        "elapsed": 0.782,
        "longname": "utumno2 > 3",
        "name": "utumno3",
        "status": "up",
        "timestamp": 1622802854.5677066
    },
    {
        "elapsed": 0.734,
        "longname": "utumno3 > 4",
        "name": "utumno4",
        "status": "up",
        "timestamp": 1622802854.56774
    },
    {
        "elapsed": 0.713,
        "longname": "utumno4 > 5",
        "name": "utumno5",
        "status": "up",
        "timestamp": 1622802854.567773
    },
    {
        "elapsed": 0.781,
        "longname": "utumno5 > 6",
        "name": "utumno5",
        "status": "up",
        "timestamp": 1622802854.567806
    },
    {
        "elapsed": 0.979,
        "longname": "utumno6 > 7",
        "name": "utumno7",
        "status": "up",
        "timestamp": 1622802854.5678384
    },
    {
        "elapsed": 0.71,
        "longname": "utumno7 > 8",
        "name": "utumno8",
        "status": "up",
        "timestamp": 1622802854.5678713
    }
]