[
    {
        "elapsed": 0.075,
        "longname": "natas0",
        "name": "natas0",
        "status": "up",
        "timestamp": 1649185458.6954138
    },
    {
        "elapsed": 0.058,
        "longname": "natas0 > 1",
        "name": "natas1",
        "status": "up",
        "timestamp": 1649185458.699005
    },
    {
        "elapsed": 0.153,
        "longname": "natas1 > 2",
        "name": "natas2",
        "status": "up",
        "timestamp": 1649185458.6993253
    },
    {
        "elapsed": 0.176,
        "longname": "natas2 > 3",
        "name": "natas3",
        "status": "up",
        "timestamp": 1649185458.6995995
    },
    {
        "elapsed": 0.213,
        "longname": "natas3 > 4",
        "name": "natas4",
        "status": "up",
        "timestamp": 1649185458.6997464
    },
    {
        "elapsed": 0.072,
        "longname": "natas4 > 5",
        "name": "natas5",
        "status": "up",
        "timestamp": 1649185458.6997705
    },
    {
        "elapsed": 0.133,
        "longname": "natas5 > 6",
        "name": "natas6",
        "status": "up",
        "timestamp": 1649185458.6997952
    },
    {
        "elapsed": 0.237,
        "longname": "natas6 > 7",
        "name": "natas7",
        "status": "up",
        "timestamp": 1649185458.69982
    },
    {
        "elapsed": 0.123,
        "longname": "natas7 > 8",
        "name": "natas8",
        "status": "up",
        "timestamp": 1649185458.6998448
    },
    {
        "elapsed": 0.191,
        "longname": "natas8 > 9",
        "name": "natas9",
        "status": "up",
        "timestamp": 1649185458.699869
    },
    {
        "elapsed": 0.198,
        "longname": "natas9 > 10",
        "name": "natas10",
        "status": "up",
        "timestamp": 1649185458.6990416
    },
    {
        "elapsed": 0.181,
        "longname": "natas10 > 11",
        "name": "natas11",
        "status": "up",
        "timestamp": 1649185458.69907
    },
    {
        "elapsed": 0.198,
        "longname": "natas11 > 12",
        "name": "natas12",
        "status": "up",
        "timestamp": 1649185458.6990979
    },
    {
        "elapsed": 0.299,
        "longname": "natas12 > 13",
        "name": "natas13",
        "status": "up",
        "timestamp": 1649185458.6991246
    },
    {
        "elapsed": 0.298,
        "longname": "natas13 > 14",
        "name": "natas14",
        "status": "up",
        "timestamp": 1649185458.6991503
    },
    {
        "elapsed": 0.175,
        "longname": "natas14 > 15",
        "name": "natas15",
        "status": "up",
        "timestamp": 1649185458.6991754
    },
    {
        "elapsed": 4.027,
        "longname": "natas15 > 16",
        "name": "natas16",
        "status": "up",
        "timestamp": 1649185458.699201
    },
    {
        "elapsed": 1.741,
        "longname": "natas16 > 17",
        "name": "natas17",
        "status": "up",
        "timestamp": 1649185458.699229
    },
    {
        "elapsed": 7.883,
        "longname": "natas17 > 18",
        "name": "natas18",
        "status": "up",
        "timestamp": 1649185458.6992729
    },
    {
        "elapsed": 1.196,
        "longname": "natas18 > 19",
        "name": "natas19",
        "status": "up",
        "timestamp": 1649185458.6992998
    },
    {
        "elapsed": 0.965,
        "longname": "natas19 > 20",
        "name": "natas20",
        "status": "up",
        "timestamp": 1649185458.699351
    },
    {
        "elapsed": 0.383,
        "longname": "natas20 > 21",
        "name": "natas21",
        "status": "up",
        "timestamp": 1649185458.6993766
    },
    {
        "elapsed": 0.362,
        "longname": "natas21 > 22",
        "name": "natas22",
        "status": "up",
        "timestamp": 1649185458.6994026
    },
    {
        "elapsed": 0.204,
        "longname": "natas22 > 23",
        "name": "natas23",
        "status": "up",
        "timestamp": 1649185458.6994276
    },
    {
        "elapsed": 0.187,
        "longname": "natas23 > 24",
        "name": "natas24",
        "status": "up",
        "timestamp": 1649185458.699453
    },
    {
        "elapsed": 0.179,
        "longname": "natas24 > 25",
        "name": "natas25",
        "status": "up",
        "timestamp": 1649185458.6994777
    },
    {
        "elapsed": 0.194,
        "longname": "natas25 > 26",
        "name": "natas26",
        "status": "up",
        "timestamp": 1649185458.6995022
    },
    {
        "elapsed": 0.252,
        "longname": "natas26 > 27",
        "name": "natas27",
        "status": "up",
        "timestamp": 1649185458.699527
    },
    {
        "elapsed": 0.269,
        "longname": "natas27 > 28",
        "name": "natas28",
        "status": "up",
        "timestamp": 1649185458.6995518
    },
    {
        "elapsed": 0.158,
        "longname": "natas28 > 29",
        "name": "natas29",
        "status": "up",
        "timestamp": 1649185458.699576
    },
    {
        "elapsed": 0.233,
        "longname": "natas29 > 30",
        "name": "natas30",
        "status": "up",
        "timestamp": 1649185458.6996236
    },
    {
        "elapsed": 0.347,
        "longname": "natas30 > 31",
        "name": "natas31",
        "status": "up",
        "timestamp": 1649185458.6996477
    },
    {
        "elapsed": 0.325,
        "longname": "natas31 > 32",
        "name": "natas32",
        "status": "up",
        "timestamp": 1649185458.6996722
    },
    {
        "elapsed": 0.33,
        "longname": "natas32 > 33",
        "name": "natas33",
        "status": "up",
        "timestamp": 1649185458.6996973
    },
    {
        "elapsed": 0.271,
        "longname": "natas33 > 34",
        "name": "natas34",
        "status": "up",
        "timestamp": 1649185458.6997218
    }
]