[
    {
        "elapsed": 2.552,
        "longname": "manpage0",
        "name": "manpage0",
        "status": "up",
        "timestamp": 1659591192.8820486
    },
    {
        "elapsed": 1.232,
        "longname": "manpage0>1",
        "name": "manpage1",
        "status": "up",
        "timestamp": 1659591192.8820791
    },
    {
        "elapsed": 1.423,
        "longname": "manpage1>2",
        "name": "manpage2",
        "status": "up",
        "timestamp": 1659591192.8821075
    },
    {
        "elapsed": 1.58,
        "longname": "manpage2>3",
        "name": "manpage3",
        "status": "up",
        "timestamp": 1659591192.8821332
    },
    {
        "elapsed": 1.365,
        "longname": "manpage3>4",
        "name": "manpage4",
        "status": "up",
        "timestamp": 1659591192.882158
    },
    {
        "elapsed": 1.52,
        "longname": "manpage4>5",
        "name": "manpage5",
        "status": "up",
        "timestamp": 1659591192.8821826
    },
    {
        "elapsed": 1.302,
        "longname": "manpage5 > 6",
        "name": "manpage6",
        "status": "up",
        "timestamp": 1659591192.8822074
    },
    {
        "elapsed": 0.003,
        "longname": "manpage6 > 7",
        "name": "manpage7",
        "status": "unknown",
        "timestamp": 1659591192.8819785
    }
]