[
    {
        "elapsed": 2.245,
        "longname": "krypton1",
        "name": "krypton1",
        "status": "up",
        "timestamp": 1661965367.552808
    },
    {
        "elapsed": 1.124,
        "longname": "krypton1 > 2",
        "name": "krypton1",
        "status": "up",
        "timestamp": 1661965367.5528674
    },
    {
        "elapsed": 1.607,
        "longname": "krypton2 > 3",
        "name": "krypton2",
        "status": "up",
        "timestamp": 1661965367.5528975
    },
    {
        "elapsed": 1.072,
        "longname": "krypton3 > 4",
        "name": "krypton3",
        "status": "up",
        "timestamp": 1661965367.5529256
    },
    {
        "elapsed": 1.102,
        "longname": "krypton4 > 5",
        "name": "krypton4",
        "status": "up",
        "timestamp": 1661965367.5529518
    },
    {
        "elapsed": 1.069,
        "longname": "krypton5 > 6",
        "name": "krypton5",
        "status": "up",
        "timestamp": 1661965367.5529766
    },
    {
        "elapsed": 1.616,
        "longname": "krypton6 > 7",
        "name": "krypton6",
        "status": "up",
        "timestamp": 1661965367.5530026
    }
]