[
    {
        "elapsed": 2.384,
        "longname": "maze0",
        "name": "maze0",
        "status": "up",
        "timestamp": 1625825001.1985743
    },
    {
        "elapsed": 3.321,
        "longname": "maze0 > 1",
        "name": "maze1",
        "status": "up",
        "timestamp": 1625825001.1986516
    },
    {
        "elapsed": 1.192,
        "longname": "maze1 > 2",
        "name": "maze2",
        "status": "up",
        "timestamp": 1625825001.1986907
    },
    {
        "elapsed": 1.23,
        "longname": "maze2 > 3",
        "name": "maze3",
        "status": "up",
        "timestamp": 1625825001.198727
    },
    {
        "elapsed": 0.653,
        "longname": "maze3 > 4",
        "name": "maze4",
        "status": "up",
        "timestamp": 1625825001.1987617
    },
    {
        "elapsed": 1.257,
        "longname": "maze4 > 5",
        "name": "maze5",
        "status": "up",
        "timestamp": 1625825001.1987967
    },
    {
        "elapsed": 0.736,
        "longname": "maze5 > 6",
        "name": "maze6",
        "status": "up",
        "timestamp": 1625825001.198831
    },
    {
        "elapsed": 1.296,
        "longname": "maze6 > 7",
        "name": "maze7",
        "status": "up",
        "timestamp": 1625825001.1988654
    },
    {
        "elapsed": 1.247,
        "longname": "maze7 > 8",
        "name": "maze8",
        "status": "up",
        "timestamp": 1625825001.1988995
    },
    {
        "elapsed": 2.808,
        "longname": "maze8 > 9",
        "name": "maze9",
        "status": "up",
        "timestamp": 1625825001.1989453
    }
]